version.py
profiles_rudderstack_bin-0.24.0.data/data/bin/pb
profiles_rudderstack_bin-0.24.0.dist-info/METADATA
profiles_rudderstack_bin-0.24.0.dist-info/WHEEL
profiles_rudderstack_bin-0.24.0.dist-info/top_level.txt
profiles_rudderstack_bin-0.24.0.dist-info/RECORD
