Metadata-Version: 2.4
Name: profiles_rudderstack_bin
Version: 0.24.0
Summary: A warehouse-native semantic modeling layer that creates unified customer profiles in your data warehouse
Home-page: https://www.rudderstack.com/
Author: RudderStack
Author-email: profiles@rudderstack.com
Maintainer: RudderStack
Project-URL: Documentation, https://www.rudderstack.com/docs/profiles/overview/
Keywords: rudderstack,profiles,semantic modeling,identity stitching,data modeling,warehouse transformations,transformation,data engineering,c360
Classifier: Development Status :: 5 - Production/Stable
Classifier: Programming Language :: Python :: 3
Classifier: Intended Audience :: Developers
Classifier: License :: OSI Approved :: MIT License
Classifier: Operating System :: MacOS :: MacOS X
Classifier: Operating System :: POSIX :: Linux
Classifier: Operating System :: Microsoft :: Windows
Dynamic: author
Dynamic: author-email
Dynamic: classifier
Dynamic: description
Dynamic: description-content-type
Dynamic: home-page
Dynamic: keywords
Dynamic: maintainer
Dynamic: project-url
Dynamic: summary
